sc_inclusive_balance_detail_analysis/__init__.py
sc_inclusive_balance_detail_analysis/main.py
sc_inclusive_balance_detail_analysis/manifest_utils.py
sc_inclusive_balance_detail_analysis/analyzer/__init__.py
sc_inclusive_balance_detail_analysis/analyzer/base_analyzer.py
sc_inclusive_balance_detail_analysis/analyzer/inclusive_balance_detail_analyzer.py
sc_inclusive_balance_detail_analysis/summary/__init__.py
sc_inclusive_balance_detail_analysis/summary/branch_summary_analyzer.py
sc_inclusive_balance_detail_analysis/summary/manager_summary_analyzer.py
sc_inclusive_balance_detail_analysis/tests/__init__.py
sc_inclusive_balance_detail_analysis/tests/sample_config/production.yml
sc_inclusive_balance_detail_analysis-0.0.6.dist-info/LICENSE
sc_inclusive_balance_detail_analysis-0.0.6.dist-info/METADATA
sc_inclusive_balance_detail_analysis-0.0.6.dist-info/WHEEL
sc_inclusive_balance_detail_analysis-0.0.6.dist-info/entry_points.txt
sc_inclusive_balance_detail_analysis-0.0.6.dist-info/top_level.txt
sc_inclusive_balance_detail_analysis-0.0.6.dist-info/RECORD
